tsp_solver/__init__.py
tsp_solver/greedy.py
tsp_solver/greedy_numpy.py
tsp_solver/util.py
tsp_solver/demo/__init__.py
tsp_solver/demo/image2point_cloud.py
tsp_solver/demo/numpy2svg.py
tsp_solver/demo/tsp.py
tsp_solver2-0.4.1.data/scripts/tsp_demo
tsp_solver2-0.4.1.data/scripts/tsp_numpy2svg
tsp_solver2-0.4.1.dist-info/LICENSE
tsp_solver2-0.4.1.dist-info/LICENSE~
tsp_solver2-0.4.1.dist-info/METADATA
tsp_solver2-0.4.1.dist-info/WHEEL
tsp_solver2-0.4.1.dist-info/top_level.txt
tsp_solver2-0.4.1.dist-info/RECORD
