Metadata-Version: 2.1
Name: tsp_solver2
Version: 0.4.1
Summary: Greedy, suboptimal solver for the Travelling Salesman Problem
Home-page: https://github.com/dmishin/tsp-solver
Author: Dmitry Shintyakov
Author-email: shintyakov@gmail.com
License: free domain
Keywords: travelling salesman problem,optimization
Platform: UNKNOWN
Classifier: License :: Public Domain
Classifier: Operating System :: OS Independent
Classifier: Programming Language :: Python :: 2.7
Classifier: Programming Language :: Python :: 3.4
Classifier: Programming Language :: Python :: 3.5
Classifier: Programming Language :: Python :: 3.6
Classifier: Programming Language :: Python :: 3.7
